example_pkg/__init__.py
anzony.quispe-0.0.1.dist-info/LICENSE
anzony.quispe-0.0.1.dist-info/METADATA
anzony.quispe-0.0.1.dist-info/WHEEL
anzony.quispe-0.0.1.dist-info/top_level.txt
anzony.quispe-0.0.1.dist-info/RECORD
