Metadata-Version: 2.1
Name: anzony.quispe
Version: 0.0.1
Summary: This is just a simple calculator
Home-page: https://github.com/pypa/sampleproject
Author: Anzony
Author-email: futurolos9@gmail.com
License: UNKNOWN
Platform: UNKNOWN
Classifier: Programming Language :: Python :: 3
Classifier: License :: OSI Approved :: MIT License
Classifier: Operating System :: OS Independent
Requires-Python: >=3.6
